setup.py
thrift_amqp_tornado/__init__.py
thrift_amqp_tornado/constant.py
thrift_amqp_tornado/server.py
thrift_amqp_tornado/transport.py
thrift_amqp_tornado.egg-info/PKG-INFO
thrift_amqp_tornado.egg-info/SOURCES.txt
thrift_amqp_tornado.egg-info/dependency_links.txt
thrift_amqp_tornado.egg-info/requires.txt
thrift_amqp_tornado.egg-info/top_level.txt