Metadata-Version: 1.0
Name: thrift-amqp-tornado
Version: 0.1.3
Summary: Thirft transport implementation over the AMQP protocol
Home-page: https://github.com/upfluence/thrift-amqp-tornado
Author: Alexis Montagne
Author-email: alexis.montagne@upfluence.co
License: UNKNOWN
Platform: UNKNOWN
